azure_teambots/__init__.py
azure_teambots/adapters.py
azure_teambots/conf.py
azure_teambots/config.py
azure_teambots/exceptions.py
azure_teambots/graph.py
azure_teambots/models.py
azure_teambots/py.typed
azure_teambots/service.py
azure_teambots/version.py
azure_teambots/bots/BadgeBot.py
azure_teambots/bots/ChatBot.py
azure_teambots/bots/ProfileBot.py
azure_teambots/bots/__init__.py
azure_teambots/bots/abstract.py
azure_teambots/bots/base.py
azure_teambots/bots/card.py
azure_teambots/bots/channel.py
azure_teambots/bots/echo.py
azure_teambots/bots/file.py
azure_teambots/bots/listener.py
azure_teambots/bots/private.py
azure_teambots/bots/wizard.py
azure_teambots/bots/dialogs/__init__.py
azure_teambots/bots/dialogs/badge.py
azure_teambots/bots/dialogs/profile.py
azure_teambots/bots/helpers/__init__.py
azure_teambots/bots/interfaces/__init__.py
azure_teambots/bots/interfaces/messages.py
azure_teambots-0.1.1.dist-info/METADATA
azure_teambots-0.1.1.dist-info/WHEEL
azure_teambots-0.1.1.dist-info/top_level.txt
azure_teambots-0.1.1.dist-info/RECORD
